engagesmarter/__init__.py
engagesmarter/_auth_client.py
engagesmarter/client.py
engagesmarter/constants.py
engagesmarter/errors.py
engagesmarter/errors_handler.py
engagesmarter/py.typed
engagesmarter/resources/__init__.py
engagesmarter/resources/agents.py
engagesmarter/resources/base.py
engagesmarter/resources/conversations.py
engagesmarter/resources/runs.py
engagesmarter/resources/tags.py
engagesmarter/schemas/__init__.py
engagesmarter/schemas/agents.py
engagesmarter/schemas/base.py
engagesmarter/schemas/conversations.py
engagesmarter/schemas/feedback.py
engagesmarter/schemas/messages.py
engagesmarter/schemas/runs.py
engagesmarter/schemas/tags.py
engagesmarter/utils/__init__.py
engagesmarter/utils/content.py
engagesmarter/utils/pydantic.py
engagesmarter/utils/streaming.py
engagesmarter/utils/utils.py
engagesmarter_py-0.1.4.dist-info/LICENSE.md
engagesmarter_py-0.1.4.dist-info/METADATA
engagesmarter_py-0.1.4.dist-info/WHEEL
engagesmarter_py-0.1.4.dist-info/RECORD
