Metadata-Version: 2.1
Name: engagesmarter-py
Version: 0.1.4
Summary: Engage Smarter AI Platform Python client.
Home-page: https://docs.engagesmarter.ai
License: MIT
Author: Tom Dorrington Ward
Author-email: tom@engagesmarter.ai
Maintainer: Tom Dorrington Ward
Maintainer-email: tom@engagesmarter.ai
Requires-Python: >=3.9
Classifier: License :: OSI Approved :: MIT License
Classifier: Programming Language :: Python :: 3
Classifier: Programming Language :: Python :: 3.9
Classifier: Programming Language :: Python :: 3.10
Classifier: Programming Language :: Python :: 3.11
Classifier: Programming Language :: Python :: 3.12
Requires-Dist: httpx (>=0.19.0)
Requires-Dist: pydantic (>=1.0.0,<3.0.0)
